claim_ai/__init__.py
claim_ai/admin.py
claim_ai/apps.py
claim_ai/models.py
claim_ai/routing.py
claim_ai/tasks.py
claim_ai/urls.py
claim_ai/utils.py
claim_ai/views.py
claim_ai/consumers/__init__.py
claim_ai/consumers/claim_consumer.py
claim_ai/evaluation/__init__.py
claim_ai/evaluation/evaluation_result.py
claim_ai/evaluation/fhir_bundle_evaluation.py
claim_ai/evaluation/predictor.py
claim_ai/evaluation/stored_resource_evaluation.py
claim_ai/evaluation/converters/__init__.py
claim_ai/evaluation/converters/base_converter.py
claim_ai/evaluation/converters/claim_response_converter_mixin.py
claim_ai/evaluation/converters/legacy_converter/__init__.py
claim_ai/evaluation/converters/legacy_converter/ai_converter.py
claim_ai/evaluation/converters/legacy_converter/claim.py
claim_ai/evaluation/converters/legacy_converter/healthcare.py
claim_ai/evaluation/converters/legacy_converter/medical_provisions.py
claim_ai/evaluation/converters/legacy_converter/patient.py
claim_ai/evaluation/converters/r4_fhir_resources/__init__.py
claim_ai/evaluation/converters/r4_fhir_resources/adjudication_converter.py
claim_ai/evaluation/converters/r4_fhir_resources/ai_converter.py
claim_ai/evaluation/converters/r4_fhir_resources/bundle_converter.py
claim_ai/evaluation/converters/r4_fhir_resources/response_converter.py
claim_ai/evaluation/converters/r4_fhir_resources/fhir_converters/__init__.py
claim_ai/evaluation/converters/r4_fhir_resources/fhir_converters/abstract_converters.py
claim_ai/evaluation/converters/r4_fhir_resources/fhir_converters/activity_definition.py
claim_ai/evaluation/converters/r4_fhir_resources/fhir_converters/claim.py
claim_ai/evaluation/converters/r4_fhir_resources/fhir_converters/dataclasses.py
claim_ai/evaluation/converters/r4_fhir_resources/fhir_converters/group.py
claim_ai/evaluation/converters/r4_fhir_resources/fhir_converters/healthcare.py
claim_ai/evaluation/converters/r4_fhir_resources/fhir_converters/medication.py
openimis_be_claim_ai-2.0.0.dist-info/LICENSE
openimis_be_claim_ai-2.0.0.dist-info/METADATA
openimis_be_claim_ai-2.0.0.dist-info/WHEEL
openimis_be_claim_ai-2.0.0.dist-info/top_level.txt
openimis_be_claim_ai-2.0.0.dist-info/RECORD
