Metadata-Version: 2.1
Name: openimis-be-claim-ai
Version: 2.0.0
Summary: The openIMIS Backend Claim AI reference module.
Home-page: https://openimis.org/
Author: Damian Borowiecki
Author-email: dborowiecki@soldevelo.com
License: GNU AGPL v3
Platform: UNKNOWN
Classifier: Environment :: Web Environment
Classifier: Framework :: Django
Classifier: Framework :: Django :: 2.1
Classifier: Intended Audience :: Developers
Classifier: License :: OSI Approved :: GNU Affero General Public License v3
Classifier: Operating System :: OS Independent
Classifier: Programming Language :: Python
Classifier: Programming Language :: Python :: 3.6
Classifier: Programming Language :: Python :: 3.7
License-File: LICENSE
Requires-Dist: django (~=3.0.14)
Requires-Dist: django-db-signals
Requires-Dist: djangorestframework
Requires-Dist: joblib
Requires-Dist: scikit-learn (==0.23.2)
Requires-Dist: xgboost (==1.3.3)
Requires-Dist: category-encoders
Requires-Dist: pandas (==1.1.4)
Requires-Dist: pandarallel (==1.5.5)
Requires-Dist: gevent (==21.12.0)
